Metadata-Version: 2.1
Name: amphetype
Version: 1.2.1
Summary: Advanced typing practice program
Home-page: https://gitlab.com/franksh/amphetype
Author: Frank S. Hestvik
Author-email: tristesse@gmail.com
License: GPL3
Keywords: typing,keyboard,typist,wpm,colemak,dvorak,workman
Platform: UNKNOWN
Classifier: Development Status :: 5 - Production/Stable
Classifier: License :: OSI Approved :: GNU General Public License v3 (GPLv3)
Classifier: Intended Audience :: End Users/Desktop
Classifier: Programming Language :: Python :: 3
Requires-Python: >=3.6
License-File: LICENSE
Requires-Dist: PyQt5
Requires-Dist: translitcodec
Requires-Dist: editdistance
